seqthetic/__init__.py
seqthetic/dataset.py
seqthetic/dependencies/__init__.py
seqthetic/dependencies/adapter.py
seqthetic/dependencies/base.py
seqthetic/dependencies/fbm.py
seqthetic/dependencies/function.py
seqthetic/dependencies/random.py
seqthetic/mapping.py
seqthetic/range.py
seqthetic/seed.py
seqthetic/spec_variation.py
seqthetic/synthesis_spec.py
seqthetic/synthesizer.py
seqthetic/utils.py
seqthetic/vary/__init__.py
seqthetic/vary/compose_ops.py
seqthetic/vary/compute_ops.py
seqthetic/vary/domain_ops.py
seqthetic/vary/transform.py
seqthetic/vary/variation.py
seqthetic/vary/variator.py
seqthetic/vocabulary.py
seqthetic-0.1.11.dist-info/METADATA
seqthetic-0.1.11.dist-info/WHEEL
seqthetic-0.1.11.dist-info/RECORD
