Metadata-Version: 2.1
Name: seqthetic
Version: 0.1.11
Summary: Creates sequence data for pretraining and benchmarking sequence models
Author: Shom
Author-email: shaomi_lin@126.com
Requires-Python: >=3.10,<3.11
Classifier: Programming Language :: Python :: 3
Classifier: Programming Language :: Python :: 3.10
Requires-Dist: dill (>=0.3.8,<0.4.0)
Requires-Dist: flake8 (>=7.0.0,<8.0.0)
Requires-Dist: joblib (>=1.4.2,<2.0.0)
Requires-Dist: joblib-progress (>=1.0.5,<2.0.0)
Requires-Dist: jupyter (>=1.0.0,<2.0.0)
Requires-Dist: more-itertools (>=10.2.0,<11.0.0)
Requires-Dist: nanoid (>=2.0.0,<3.0.0)
Requires-Dist: numpy (>=1.26.4,<2.0.0)
Requires-Dist: pandas (>=2.2.2,<3.0.0)
Requires-Dist: plotly (>=5.21.0,<6.0.0)
Requires-Dist: pydantic (>=2.7.0,<3.0.0)
Requires-Dist: stochastic (>=0.7.0,<0.8.0)
